{
  "config": {
    "step": {
      "confirm": {
        "description": "[%key:common::config_flow::description::confirm_setup%]"
      }
    },
    "abort": {
      "single_instance_allowed": "[%key:common::config_flow::abort::single_instance_allowed%]",
      "no_devices_found": "[%key:common::config_flow::abort::no_devices_found%]"
    }
  },
  "exceptions": {
    "input_entity_not_linked": {
      "message": "Input entity {input_entity_id} is not linked in integration options"
    },
    "input_not_active": {
      "message": "Input {input} is not active"
    }
  }
}
